[
    {
      "nombre": "Morph Close",
      "funcion": "cv2.morphologyEx",
      "group": "Morphology",
      "input images": 1,
      "output images": 1,
      "parameters_order": ["op","kernel"],
      "outputs_order": ["dst"],
      "widgets": [{
          "assign": [{"text":"cv2.MORPH_CLOSE", "label": "op"},
                     {"text":"cv2.getStructuringElement(cv2.MORPH_CROSS, (15,15))", "label": "kernel"}  ]
                }],
        "information": [{
            "function": "",
            "parameters": "\n"
        }]
    }        
]
